pyxtal_step/__init__.py
pyxtal_step/_version.py
pyxtal_step/installer.py
pyxtal_step/metadata.py
pyxtal_step/pyxtal.py
pyxtal_step/pyxtal_parameters.py
pyxtal_step/pyxtal_step.py
pyxtal_step/tk_pyxtal.py
pyxtal_step/data/configuration.txt
pyxtal_step/data/references.bib
pyxtal_step/data/seamm-pyxtal.yml
pyxtal_step-2021.7.29.dist-info/AUTHORS.rst
pyxtal_step-2021.7.29.dist-info/LICENSE
pyxtal_step-2021.7.29.dist-info/METADATA
pyxtal_step-2021.7.29.dist-info/WHEEL
pyxtal_step-2021.7.29.dist-info/entry_points.txt
pyxtal_step-2021.7.29.dist-info/top_level.txt
pyxtal_step-2021.7.29.dist-info/zip-safe
pyxtal_step-2021.7.29.dist-info/RECORD
