Metadata-Version: 2.1
Name: pyxtal-step
Version: 2021.7.29
Summary: A SEAMM plugin for PyXtal for building atomic and molecular crystals.
Home-page: https://github.com/qzhu2017/pyxtal_step
Author: Qiang Zhu
Author-email: qiang.zhu@unlv.edu
License: MIT
Keywords: SEAMM,plug-in,flowchart,PyXtal,crystals
Platform: Linux
Platform: Mac OS-X
Platform: Unix
Platform: Windows
Classifier: Development Status :: 5 - Production/Stable
Classifier: Intended Audience :: Science/Research
Classifier: Topic :: Scientific/Engineering :: Chemistry
Classifier: Topic :: Scientific/Engineering :: Physics
Classifier: License :: OSI Approved :: MIT License
Classifier: Natural Language :: English
Classifier: Programming Language :: Python :: 3 :: Only
Classifier: Programming Language :: Python :: 3.8
Classifier: Programming Language :: Python :: 3.9
Requires-Dist: chemical-formula
Requires-Dist: seamm
Requires-Dist: seamm-util
Requires-Dist: seamm-widgets
